README.md
setup.py
docker_registry_util/__init__.py
docker_registry_util/cache.py
docker_registry_util/cli.py
docker_registry_util/client.py
docker_registry_util/digest.py
docker_registry_util/query.py
docker_registry_util/remover.py
docker_registry_util.egg-info/PKG-INFO
docker_registry_util.egg-info/SOURCES.txt
docker_registry_util.egg-info/dependency_links.txt
docker_registry_util.egg-info/entry_points.txt
docker_registry_util.egg-info/requires.txt
docker_registry_util.egg-info/top_level.txt
test/__init__.py
test/data.py
test/test_cache.py
test/test_query.py